pds/__init__.py
pds/store.py
python_pds-0.1.1.dist-info/licenses/LICENSE
python_pds-0.1.1.dist-info/METADATA
python_pds-0.1.1.dist-info/WHEEL
python_pds-0.1.1.dist-info/top_level.txt
python_pds-0.1.1.dist-info/RECORD
