Metadata-Version: 2.4
Name: python-pds
Version: 0.1.1
Summary: Portable Data Store for efficient storage and retrieval of JSON-serializable objects with Zstandard compression.
Author: Oliver Kiss, Markus Mobius
License: MIT License
Project-URL: Homepage, https://github.com/kiss-oliver/PDS
Project-URL: Repository, https://github.com/kiss-oliver/PDS
Project-URL: Bug Tracker, https://github.com/kiss-oliver/PDS/issues
Keywords: pds,storage,key-value,zstandard,zstd,compression,json,datastore
Classifier: Development Status :: 3 - Alpha
Classifier: Intended Audience :: Developers
Classifier: License :: OSI Approved :: MIT License
Classifier: Operating System :: OS Independent
Classifier: Programming Language :: Python :: 3
Classifier: Programming Language :: Python :: 3.7
Classifier: Programming Language :: Python :: 3.8
Classifier: Programming Language :: Python :: 3.9
Classifier: Programming Language :: Python :: 3.10
Classifier: Programming Language :: Python :: 3.11
Classifier: Programming Language :: Python :: 3.12
Classifier: Programming Language :: Python :: 3.13
Classifier: Topic :: Database
Classifier: Topic :: System :: Archiving :: Compression
Classifier: Topic :: Software Development :: Libraries :: Python Modules
Requires-Python: >=3.7
License-File: LICENSE
Requires-Dist: zstandard
Dynamic: license-file
